odoo/addons/account_move_line_cumulated_balance/README.rst
odoo/addons/account_move_line_cumulated_balance/__init__.py
odoo/addons/account_move_line_cumulated_balance/__manifest__.py
odoo/addons/account_move_line_cumulated_balance/i18n/account_move_line_cumulated_balance.pot
odoo/addons/account_move_line_cumulated_balance/i18n/es.po
odoo/addons/account_move_line_cumulated_balance/models/__init__.py
odoo/addons/account_move_line_cumulated_balance/models/account_move_line.py
odoo/addons/account_move_line_cumulated_balance/readme/CONFIGURE.rst
odoo/addons/account_move_line_cumulated_balance/readme/CONTRIBUTORS.rst
odoo/addons/account_move_line_cumulated_balance/readme/DESCRIPTION.rst
odoo/addons/account_move_line_cumulated_balance/readme/ROADMAP.rst
odoo/addons/account_move_line_cumulated_balance/readme/USAGE.rst
odoo/addons/account_move_line_cumulated_balance/static/description/icon.png
odoo/addons/account_move_line_cumulated_balance/static/description/index.html
odoo/addons/account_move_line_cumulated_balance/tests/__init__.py
odoo/addons/account_move_line_cumulated_balance/tests/test_account_move_line_cumulated_balance.py
odoo/addons/account_move_line_cumulated_balance/views/account_move_views.xml
odoo13_addon_account_move_line_cumulated_balance-13.0.1.0.1.dist-info/METADATA
odoo13_addon_account_move_line_cumulated_balance-13.0.1.0.1.dist-info/WHEEL
odoo13_addon_account_move_line_cumulated_balance-13.0.1.0.1.dist-info/top_level.txt
odoo13_addon_account_move_line_cumulated_balance-13.0.1.0.1.dist-info/RECORD
